{
  "main": {
    "id": "c0d1ac80dd9e3b4e",
    "type": "split",
    "children": [
      {
        "id": "395acb0fa20042c6",
        "type": "tabs",
        "children": [
          {
            "id": "8fe4f9b0f7d6553f",
            "type": "leaf",
            "state": {
              "type": "empty",
              "state": {}
            }
          }
        ]
      }
    ],
    "direction": "vertical"
  },
  "left": {
    "id": "71963580dfae1b07",
    "type": "split",
    "children": [
      {
        "id": "3619522fa8caad0e",
        "type": "tabs",
        "children": [
          {
            "id": "394ff5b744e1c774",
            "type": "leaf",
            "state": {
              "type": "file-explorer",
              "state": {
                "sortOrder": "alphabetical"
              }
            }
          },
          {
            "id": "2b83db17633d596b",
            "type": "leaf",
            "state": {
              "type": "search",
              "state": {
                "query": "",
                "matchingCase": false,
                "explainSearch": false,
                "collapseAll": false,
                "extraContext": false,
                "sortOrder": "alphabetical"
              }
            }
          },
          {
            "id": "30930dfec4b4506b",
            "type": "leaf",
            "state": {
              "type": "bookmarks",
              "state": {}
            }
          }
        ]
      }
    ],
    "direction": "horizontal",
    "width": 300
  },
  "right": {
    "id": "07f6f20384f475cb",
    "type": "split",
    "children": [
      {
        "id": "12303a7f9fcbe758",
        "type": "tabs",
        "children": [
          {
            "id": "1366b3d7314139a1",
            "type": "leaf",
            "state": {
              "type": "backlink",
              "state": {
                "collapseAll": false,
                "extraContext": false,
                "sortOrder": "alphabetical",
                "showSearch": false,
                "searchQuery": "",
                "backlinkCollapsed": false,
                "unlinkedCollapsed": true
              }
            }
          },
          {
            "id": "74153e37cd25f603",
            "type": "leaf",
            "state": {
              "type": "outgoing-link",
              "state": {
                "linksCollapsed": false,
                "unlinkedCollapsed": true
              }
            }
          },
          {
            "id": "a29a8cd6a902e72b",
            "type": "leaf",
            "state": {
              "type": "tag",
              "state": {
                "sortOrder": "frequency",
                "useHierarchy": true
              }
            }
          },
          {
            "id": "87f2e1eb9a371acf",
            "type": "leaf",
            "state": {
              "type": "outline",
              "state": {}
            }
          }
        ]
      }
    ],
    "direction": "horizontal",
    "width": 300,
    "collapsed": true
  },
  "left-ribbon": {
    "hiddenItems": {
      "switcher:Open quick switcher": false,
      "graph:Open graph view": false,
      "canvas:Create new canvas": false,
      "daily-notes:Open today's daily note": false,
      "templates:Insert template": false,
      "command-palette:Open command palette": false
    }
  },
  "active": "8fe4f9b0f7d6553f",
  "lastOpenFiles": [
    "Trigger Creation.md",
    "Table population.md",
    "Table creation.md",
    "Pasted image 20231016144925.png",
    "Pasted image 20231016144958.png",
    "Pasted image 20231016124556.png.md",
    "Aggiunta colonna data.md"
  ]
}